wiopy/AsyncWIO.py
wiopy/WalmartIO.py
wiopy/WalmartResponse.py
wiopy/__init__.py
wiopy/utils/__init__.py
wiopy/utils/arguments.py
wiopy/utils/cache.py
wiopy/utils/errors.py
wiopy-1.1.1.dist-info/METADATA
wiopy-1.1.1.dist-info/WHEEL
wiopy-1.1.1.dist-info/licenses/LICENSE
wiopy-1.1.1.dist-info/RECORD
