Metadata-Version: 2.4
Name: WIOpy
Version: 1.1.1
Summary: A Python wrapper for the Walmart IO API
Project-URL: Homepage, https://github.com/CoderJoshDK/WIOpy
Project-URL: Bug Reports, https://github.com/CoderJoshDK/WIOpy/issues
Project-URL: Source, https://github.com/CoderJoshDK/WIOpy
Author: CoderJoshDK
License: MIT License
License-File: LICENSE
Keywords: AIOHTTP,API,Affiliate,Async,Walmart,WalmartIO,Wrapper
Classifier: Development Status :: 5 - Production/Stable
Classifier: Intended Audience :: Developers
Classifier: License :: OSI Approved :: MIT License
Classifier: Natural Language :: English
Classifier: Operating System :: OS Independent
Classifier: Programming Language :: Python :: 3.8
Classifier: Programming Language :: Python :: 3.9
Classifier: Programming Language :: Python :: 3.10
Classifier: Programming Language :: Python :: 3.11
Classifier: Topic :: Internet
Classifier: Topic :: Software Development :: Libraries
Classifier: Topic :: Software Development :: Libraries :: Python Modules
Classifier: Topic :: Utilities
Classifier: Typing :: Typed
Requires-Python: >=3.8
Requires-Dist: aiohttp
Requires-Dist: pycryptodome
Requires-Dist: requests
Provides-Extra: dev
Requires-Dist: pre-commit; extra == 'dev'
Requires-Dist: ruff; extra == 'dev'
